tinydataflow/__init__.py
tinydataflow/core.py
tinydataflow/connectors/__init__.py
tinydataflow/connectors/readers.py
tinydataflow/connectors/selectors.py
tinydataflow/transformers/__init__.py
tinydataflow/transformers/basic.py
tinydataflow/transformers/senders.py
tinydataflow/transformers/writers.py
tinydataflow-0.0.8.dist-info/LICENSE
tinydataflow-0.0.8.dist-info/METADATA
tinydataflow-0.0.8.dist-info/WHEEL
tinydataflow-0.0.8.dist-info/top_level.txt
tinydataflow-0.0.8.dist-info/RECORD
