Metadata-Version: 2.1
Name: tinydataflow
Version: 0.0.8
Summary: biblioteca Python simples e extensível que facilita a criação e execução de pipelines de transformação de dados e automação de processos
Home-page: https://github.com/ismaelnjr/tinyflow-project.git
Author: Ismael Nascimento
Author-email: ismaelnjr@icloud.com.br
License: MIT
Keywords: data flow transformation pipeline
Classifier: Programming Language :: Python :: 3
Classifier: License :: OSI Approved :: MIT License
Classifier: Operating System :: OS Independent
Requires-Python: >=3.8
License-File: LICENSE
